cs2solutions/H_inf.py
cs2solutions/NLC.py
cs2solutions/Qparam.py
cs2solutions/__init__.py
cs2solutions/aircraft.py
cs2solutions/cs.py
cs2solutions/cs2bot.py
cs2solutions/decomp.py
cs2solutions/discretization.py
cs2solutions/duckiebot.py
cs2solutions/inf_pkg.py
cs2solutions/intro.py
cs2solutions/intromimo.py
cs2solutions/lqg.py
cs2solutions/lqrfeedback.py
cs2solutions/morse.py
cs2solutions/norms.py
cs2solutions/plot.py
cs2solutions/test.py
cs2solutions-0.10.0.dist-info/LICENSE
cs2solutions-0.10.0.dist-info/METADATA
cs2solutions-0.10.0.dist-info/WHEEL
cs2solutions-0.10.0.dist-info/top_level.txt
cs2solutions-0.10.0.dist-info/RECORD
