Metadata-Version: 2.1
Name: cs2solutions
Version: 0.10.0
Summary: A package containing solutions for the CS2 lecture at ETH Zürich
Author-email: Niclas Scheuer <nscheuer@ethz.ch>, Kalle Laitinen <klaitinen@ethz.ch>, Dejan Milojevic <dejanmi@ethz.ch>
Maintainer-email: Kalle Laitinen <klaitinen@ethz.ch>, Niclas Scheuer <nscheuer@ethz.ch>
License: GNU GENERAL PUBLIC LICENSE
Project-URL: Homepage, https://idsc.ethz.ch/education/lectures/control-systems-ii.html
Project-URL: Repository, https://github.com/idsc-frazzoli/cs2solutions
Project-URL: Notebooks, https://github.com/idsc-frazzoli/CS2-2024-notebooks
Classifier: Programming Language :: Python :: 3
Classifier: Operating System :: OS Independent
Classifier: Development Status :: 5 - Production/Stable
Classifier: Intended Audience :: Education
Classifier: License :: OSI Approved :: GNU General Public License v3 (GPLv3)
Requires-Python: >=3.9
License-File: LICENSE
Requires-Dist: control
Requires-Dist: matplotlib
Requires-Dist: numpy
Requires-Dist: scipy
Requires-Dist: sympy
Requires-Dist: pandas
